{"version":1,"resource":"file:///home/Raj/.config/hypr/hyprpaper.conf","entries":[{"id":"7JZ8.conf","timestamp":1750618131539},{"id":"46y3.conf","timestamp":1750618242822},{"id":"sXAw.conf","timestamp":1750618268725},{"id":"gljL.conf","timestamp":1750618302750},{"id":"70tt.conf","timestamp":1750618459929},{"id":"qSK5.conf","timestamp":1750643465567},{"id":"HBEJ.conf","timestamp":1750643509392},{"id":"2RUs.conf","timestamp":1750793782333},{"id":"lwqe.conf","timestamp":1750794887993},{"id":"O175.conf","timestamp":1750795029848},{"id":"Lu02.conf","timestamp":1750795045205},{"id":"PIrP.conf","timestamp":1750795101973},{"id":"6wHP.conf","timestamp":1750874337468},{"id":"xydl.conf","timestamp":1750874838588},{"id":"9dCI.conf","timestamp":1750874861292},{"id":"lqd4.conf","timestamp":1750876661627},{"id":"sgWm.conf","timestamp":1751913914695},{"id":"zzHV.conf","timestamp":1751913942309},{"id":"meZO.conf","timestamp":1751913976895},{"id":"H4Am.conf","timestamp":1751914179961},{"id":"zXf4.conf","timestamp":1752452375502}]}